discord_app/__init__.py
discord_app/application.py
discord_app/channel.py
discord_app/discord_types.py
discord_app/emoji.py
discord_app/guild.py
discord_app/guild_scheduled_event.py
discord_app/guild_template.py
discord_app/interaction.py
discord_app/invite.py
discord_app/presence.py
discord_app/py.typed
discord_app/stage_instance.py
discord_app/sticker.py
discord_app/user.py
discord_app/voice.py
discord_app/webhook.py
discord_app-0.0.1a1.dist-info/LICENSE
discord_app-0.0.1a1.dist-info/WHEEL
discord_app-0.0.1a1.dist-info/METADATA
discord_app-0.0.1a1.dist-info/RECORD
