Metadata-Version: 2.1
Name: discord-app
Version: 0.0.1a1
Summary: Discord Interaction Application framework for Python
Home-page: https://github.com/jacky9813/discord_app
License: MIT
Author: JackyCCC
Author-email: jacky9813@hotmail.com
Requires-Python: >=3.9,<4
Classifier: License :: OSI Approved :: MIT License
Classifier: Operating System :: OS Independent
Classifier: Programming Language :: Python :: 3
Classifier: Programming Language :: Python :: 3 :: Only
Classifier: Programming Language :: Python :: 3.10
Classifier: Programming Language :: Python :: 3.9
Requires-Dist: Flask (>=2.1.1,<3.0.0)
Requires-Dist: PyNaCl (>=1.4.0,<2.0.0)
Requires-Dist: requests (>=2.27.1,<3.0.0)
Project-URL: Repository, https://github.com/jacky9813/discord_app
